Metadata-Version: 1.0
Name: teamsilly
Version: 0.1.0
Summary: Teams Messaging through Inbound Webhook
Home-page: https://github.com/droberin/teamsilly
Author: Roberto Salgado
Author-email: drober@gmail.com
License: MIT
Platform: UNKNOWN
